wordsmash/__init__.py
wordsmash/__main__.py
wordsmash/attacks.py
wordsmash/crawler.py
WordSmash-0.0.1.dist-info/LICENCE
WordSmash-0.0.1.dist-info/METADATA
WordSmash-0.0.1.dist-info/WHEEL
WordSmash-0.0.1.dist-info/entry_points.txt
WordSmash-0.0.1.dist-info/top_level.txt
WordSmash-0.0.1.dist-info/RECORD
