Metadata-Version: 2.1
Name: WordSmash
Version: 0.0.1
Summary: "Your WordPress site's best friend"
Author: The Archivist
Keywords: wordpress,attack
Classifier: Programming Language :: Python :: 3
Classifier: License :: OSI Approved :: zlib/libpng License
Classifier: Operating System :: POSIX :: Linux
Classifier: Operating System :: Microsoft :: Windows
Classifier: Operating System :: MacOS
Requires-Python: >=3.9
License-File: LICENCE
Requires-Dist: argparse
Requires-Dist: bs4
Requires-Dist: dnspython
Requires-Dist: requests
